cdktest.py
cdktest-0.0.1.dist-info/LICENSE
cdktest-0.0.1.dist-info/METADATA
cdktest-0.0.1.dist-info/WHEEL
cdktest-0.0.1.dist-info/top_level.txt
cdktest-0.0.1.dist-info/RECORD
