Metadata-Version: 2.1
Name: cdktest
Version: 0.0.1
Summary: Simple python test helper for AWS CDK
Author-email: leunguu <liangy3928@gmail.com>
License: Apache-2.0
Project-URL: homepage, https://github.com/LEUNGUU/cdk-python-testing-helper
Project-URL: repository, https://github.com/LEUNGUU/cdk-python-testing-helper
Keywords: CDK,AWS,Python,Test,Helper
Classifier: Programming Language :: Python :: 3
Classifier: License :: OSI Approved :: MIT License
Classifier: Operating System :: OS Independent
Requires-Python: >=3.10
License-File: LICENSE
Requires-Dist: aws-cdk-lib (<3.0.0,>=2.1.0)
Requires-Dist: constructs (<11.0.0,>=10.0.5)
